{
  "version": 2,
  "projects": {
    "cc-cli": "apps/cc-cli",
    "data-access-cc": "libs/data-access/cc",
    "data-access-discourse": "libs/data-access/discourse",
    "data-access-github": "libs/data-access/github",
    "data-access-khoros": "libs/data-access/khoros",
    "data-access-neo4j": "libs/data-access/neo4j",
    "feature-ninja-leaderboard": "libs/feature/ninja-leaderboard",
    "feature-person": "libs/feature/person",
    "feature-release-notes": "libs/feature/release-notes",
    "feature-twin4j": "libs/feature/twin4j",
    "graphql-types": "libs/graphql-types",
    "model": "libs/model",
    "nest-neo4j-dbms": "libs/nest/neo4j-dbms",
    "prototype-cc-show": "apps/prototype/cc-show",
    "prototype-cc-show-e2e": "apps/prototype/cc-show-e2e",
    "prototype-daisy": "apps/prototype/daisy",
    "prototype-khoros": "apps/prototype/khoros",
    "prototype-neo4j-profile": "apps/prototype/neo4j-profile",
    "server-cc-api": "apps/server/cc-api",
    "server-cc-nest": "apps/server/cc-nest",
    "server-greta-bot": "apps/server/greta-bot",
    "ui": "libs/ui",
    "util-arbitrary": "libs/util/arbitrary"
  },
  "$schema": "./node_modules/nx/schemas/workspace-schema.json"
}
